concealed/__init__.py
concealed/configuration.py
concealed/decode.py
concealed/encode.py
concealed/main.py
concealed/data/config.ini
concealed-2.0.0.dist-info/METADATA
concealed-2.0.0.dist-info/WHEEL
concealed-2.0.0.dist-info/top_level.txt
concealed-2.0.0.dist-info/RECORD
