Metadata-Version: 2.1
Name: concealed
Version: 2.0.0
Summary: python util module to provide encryption and decryption using steganography using the least significant bits of the RGB values of an image on top of advanced encryption standard.
Home-page: https://github.com/thepmsquare/concealed
Author: thePmSquare
Author-email: thepmsquare@gmail.com
Classifier: Development Status :: 3 - Alpha
Classifier: Intended Audience :: Developers
Classifier: License :: OSI Approved :: MIT License
Classifier: Programming Language :: Python :: 3
Classifier: Programming Language :: Python :: 3.9
Requires-Dist: Pillow >=8.3.1
Requires-Dist: cryptography >=41.0.4
